{
  "generator-jhipster": {
    "applicationType": "monolith",
    "authenticationType": "jwt",
    "baseName": "streaming",
    "blueprints": [],
    "buildTool": "gradle",
    "cacheProvider": "ehcache",
    "clientFramework": "no",
    "clientPackageManager": "npm",
    "clientTheme": "none",
    "clientThemeVariant": "",
    "creationTimestamp": 1666189850798,
    "databaseType": "sql",
    "devDatabaseType": "postgresql",
    "dtoSuffix": "DTO",
    "enableGradleEnterprise": false,
    "enableHibernateCache": true,
    "enableSwaggerCodegen": false,
    "enableTranslation": true,
    "entities": ["Film", "Episode", "Person"],
    "entitySuffix": "",
    "jhiPrefix": "jhi",
    "jhipsterVersion": "7.9.3",
    "jwtSecretKey": "Y2YzZjExZTJkODNlZmQxNGFiZjU2N2RkOTJkMDdmNWFhNmMxODRmMzc1YzY2MDU3ZTQ1NGI5NGE0M2I2NTkwODAyMjc5ZDcyYmU1ZTk3ZmNhZDQ2MzNjMDQ3NDg5YmFkYzQ4ZjhmMzY3YjVjNTcwY2MyM2IzYTA4ODQ5YmQ2MTk=",
    "languages": ["es", "en"],
    "lastLiquibaseTimestamp": 1666193686000,
    "messageBroker": false,
    "microfrontend": false,
    "microfrontends": [],
    "monorepository": true,
    "nativeLanguage": "es",
    "otherModules": [],
    "packageName": "com.anthonylldev.streaming",
    "pages": [],
    "prodDatabaseType": "postgresql",
    "reactive": false,
    "searchEngine": false,
    "serverPort": "8080",
    "serverSideOptions": [],
    "serviceDiscoveryType": "no",
    "skipCheckLengthOfIdentifier": false,
    "skipClient": true,
    "skipCommitHook": true,
    "skipFakeData": false,
    "skipUserManagement": false,
    "testFrameworks": [],
    "websocket": false,
    "withAdminUi": true
  }
}
